flashback/__init__.py
flashback/main.py
flashback/api/__init__.py
flashback/api/youtube_client.py
flashback/cli/__init__.py
flashback/cli/interface.py
flashback/models/__init__.py
flashback/models/video.py
flashback/tui/__init__.py
flashback/tui/interface.py
flashback/tui/results.py
flashback/tui/setup.py
flashback/tui/styles.tcss
flashback/utils/__init__.py
flashback/utils/config.py
ytflashback-2.30.0.dist-info/METADATA
ytflashback-2.30.0.dist-info/WHEEL
ytflashback-2.30.0.dist-info/entry_points.txt
ytflashback-2.30.0.dist-info/licenses/LICENSE
ytflashback-2.30.0.dist-info/RECORD
