Metadata-Version: 2.4
Name: ytflashback
Version: 2.30.0
Summary: A tool for searching YouTube videos by year, helping users find older content that might be buried by YouTube's algorithm
Project-URL: Homepage, https://github.com/cachebag/flashback
Project-URL: Repository, https://github.com/cachebga/flashback.git
Project-URL: Issues, https://github.com/cachebag/flashback/issues
Author-email: Akrm Al-Hakimi <alhakimiakrmj@gmail.com>
License: MIT
License-File: LICENSE
Keywords: archive,cli,search,tui,video,youtube
Classifier: Development Status :: 4 - Beta
Classifier: Intended Audience :: End Users/Desktop
Classifier: License :: OSI Approved :: MIT License
Classifier: Operating System :: OS Independent
Classifier: Programming Language :: Python :: 3
Classifier: Programming Language :: Python :: 3.7
Classifier: Programming Language :: Python :: 3.8
Classifier: Programming Language :: Python :: 3.9
Classifier: Programming Language :: Python :: 3.10
Classifier: Programming Language :: Python :: 3.11
Classifier: Programming Language :: Python :: 3.12
Classifier: Topic :: Internet :: WWW/HTTP :: Indexing/Search
Classifier: Topic :: Multimedia :: Video
Classifier: Topic :: Utilities
Requires-Python: >=3.7
Requires-Dist: click
Requires-Dist: colorama
Requires-Dist: google-api-python-client
Requires-Dist: platformdirs
Requires-Dist: python-dotenv
Requires-Dist: tabulate
Requires-Dist: textual
Provides-Extra: dev
Requires-Dist: black; extra == 'dev'
Requires-Dist: flake8; extra == 'dev'
Requires-Dist: mypy; extra == 'dev'
Requires-Dist: pytest; extra == 'dev'
